kogpt2_transformers/__init__.py
kogpt2_transformers/load_model.py
kogpt2_transformers/tokenization_kogpt2.py
kogpt2_transformers-0.4.0.dist-info/METADATA
kogpt2_transformers-0.4.0.dist-info/WHEEL
kogpt2_transformers-0.4.0.dist-info/top_level.txt
kogpt2_transformers-0.4.0.dist-info/RECORD
